[
  {
    "name": "Will",
    "price": "$0.00 Free with Audible trial"
  },
  {
    "name": "The Real Anthony Fauci: Bill Gates, Big Pharma, and the Global War on Democracy and Public…",
    "price": "$20.88"
  },
  {
    "name": "Big Shot Diary of a Wimpy Kid Book 16",
    "price": "$7.49"
  },
  {
    "name": "Go Tell the Bees That I Am Gone: A Novel (Outlander)",
    "price": "$23.71"
  },
  {
    "name": "Dune",
    "price": "$0.00 Free with Audible trial"
  },
  {
    "name": "All American Christmas",
    "price": "$18.92"
  },
  {
    "name": "Melissa & Doug Children's Book - Poke-a-Dot: Old MacDonald’s Farm (Board Book with Buttons…",
    "price": "$13.99"
  },
  {
    "name": "Atomic Habits: An Easy & Proven Way to Build Good Habits & Break Bad Ones",
    "price": "$11.98"
  },
  {
    "name": "Throne of Glass eBook Bundle: An 8 Book Bundle",
    "price": "$38.99"
  },
  {
    "name": "The 1619 Project: A New Origin Story",
    "price": "$23.17"
  },
  {
    "name": "It Ends With Us: A Novel",
    "price": "$9.47"
  },
  {
    "name": "Atlas of the Heart: Mapping Meaningful Connection and the Language of Human Experience",
    "price": "$19.48"
  },
  {
    "name": "Sold on a Monday: A Novel",
    "price": "$7.59"
  },
  {
    "name": "Laptop from Hell: Hunter Biden, Big Tech, and the Dirty Secrets the President Tried to Hide",
    "price": "$25.20"
  },
  {
    "name": "The Storyteller: Tales of Life and Music",
    "price": "$17.99"
  },
  {
    "name": "The Big Book of Silly Jokes for Kids",
    "price": "$5.99"
  },
  {
    "name": "If Animals Kissed Good Night",
    "price": "$4.44"
  },
  {
    "name": "The Christmas Pig",
    "price": "$12.49"
  },
  {
    "name": "The Eye of the World: Book One of The Wheel of Time",
    "price": "$0.00 Free with Audible trial"
  },
  {
    "name": "A Not So Meet Cute",
    "price": "$4.99"
  },
  {
    "name": "Greenlights",
    "price": "$0.00 Free with Audible trial"
  },
  {
    "name": "At First Light (Dr. Evan Wilding Book 1)",
    "price": "$4.99"
  },
  {
    "name": "I Am Confident, Brave & Beautiful: A Coloring Book for Girls",
    "price": "$6.99"
  },
  {
    "name": "Cat Kid Comic Club: Perspectives: A Graphic Novel (Cat Kid Comic Club #2): From the Creator of…",
    "price": "$8.62"
  },
  {
    "name": "The Judge's List: A Novel",
    "price": "$0.00 Free with Audible trial"
  },
  {
    "name": "Guinness World Records 2022",
    "price": "$14.97"
  },
  {
    "name": "The Very Hungry Caterpillar",
    "price": "$5.06"
  },
  {
    "name": "The Four Winds: A Novel",
    "price": "$14.99"
  },
  {
    "name": "Will",
    "price": "$0.00 Free with Audible trial"
  },
  {
    "name": "The Real Anthony Fauci: Bill Gates, Big Pharma, and the Global War on Democracy and Public Health (Children’s Health Defense)",
    "price": "$20.88"
  },
  {
    "name": "Big Shot Diary of a Wimpy Kid Book 16",
    "price": "$7.49"
  },
  {
    "name": "Go Tell the Bees That I Am Gone: A Novel (Outlander)",
    "price": "$23.71"
  },
  {
    "name": "Dune",
    "price": "$0.00 Free with Audible trial"
  },
  {
    "name": "All American Christmas",
    "price": "$18.92"
  },
  {
    "name": "Melissa & Doug Children's Book - Poke-a-Dot: Old MacDonald’s Farm (Board Book with Buttons…",
    "price": "$13.99"
  },
  {
    "name": "Atomic Habits: An Easy & Proven Way to Build Good Habits & Break Bad Ones",
    "price": "$11.98"
  },
  {
    "name": "Throne of Glass eBook Bundle: An 8 Book Bundle",
    "price": "$38.99"
  },
  {
    "name": "The 1619 Project: A New Origin Story",
    "price": "$23.17"
  },
  {
    "name": "It Ends With Us: A Novel",
    "price": "$9.47"
  },
  {
    "name": "Atlas of the Heart: Mapping Meaningful Connection and the Language of Human Experience",
    "price": "$19.48"
  },
  {
    "name": "Sold on a Monday: A Novel",
    "price": "$7.59"
  },
  {
    "name": "How to Draw 101 Animals (1)",
    "price": "$3.29"
  },
  {
    "name": "Laptop from Hell: Hunter Biden, Big Tech, and the Dirty Secrets the President Tried to Hide",
    "price": "$28.99"
  },
  {
    "name": "The Storyteller: Tales of Life and Music",
    "price": "$17.99"
  },
  {
    "name": "The Big Book of Silly Jokes for Kids",
    "price": "$5.99"
  },
  {
    "name": "If Animals Kissed Good Night",
    "price": "$4.44"
  },
  {
    "name": "The Christmas Pig",
    "price": "$12.49"
  },
  {
    "name": "The Eye of the World: Book One of The Wheel of Time",
    "price": "$0.00 Free with Audible trial"
  },
  {
    "name": "I Love You to the Moon and Back",
    "price": "$4.28"
  },
  {
    "name": "How to Catch a Mermaid",
    "price": "$4.96"
  },
  {
    "name": "A Not So Meet Cute",
    "price": "$4.99"
  },
  {
    "name": "Greenlights",
    "price": "$0.00 Free with Audible trial"
  },
  {
    "name": "At First Light (Dr. Evan Wilding Book 1)",
    "price": "$4.99"
  },
  {
    "name": "I Am Confident, Brave & Beautiful: A Coloring Book for Girls",
    "price": "$6.99"
  },
  {
    "name": "Cat Kid Comic Club: Perspectives: A Graphic Novel (Cat Kid Comic Club #2): From the Creator of…",
    "price": "$8.62"
  },
  {
    "name": "The Judge's List: A Novel",
    "price": "$0.00 Free with Audible trial"
  },
  {
    "name": "Guinness World Records 2022",
    "price": "$14.97"
  },
  {
    "name": "The Very Hungry Caterpillar",
    "price": "$5.06"
  },
  {
    "name": "The Four Winds: A Novel",
    "price": "$14.99"
  },
  {
    "name": "The Lincoln Highway: A Novel",
    "price": "$18.84"
  },
  {
    "name": "My First Learn to Write Workbook: Practice for Kids with Pen Control, Line Tracing, Letters, and More!",
    "price": "$4.53"
  },
  {
    "name": "From Crook to Cook: Platinum Recipes from Tha Boss Dogg's Kitchen (Snoop Dogg…",
    "price": "$12.74"
  },
  {
    "name": "Ignite: A Grumpy Single Dad Romance",
    "price": "$2.99"
  },
  {
    "name": "The Worst Best Friend: A Small Town Romance",
    "price": "$2.99"
  },
  {
    "name": "The Stranger in the Lifeboat: A Novel",
    "price": "$11.99"
  },
  {
    "name": "Difficult Riddles For Smart Kids: 300 Difficult Riddles And Brain Teasers Families Will Love…",
    "price": "$5.99"
  },
  {
    "name": "Will",
    "price": "$0.00 Free with Audible trial"
  },
  {
    "name": "The Real Anthony Fauci: Bill Gates, Big Pharma, and the Global War on Democracy and Public…",
    "price": "$20.88"
  },
  {
    "name": "Big Shot Diary of a Wimpy Kid Book 16",
    "price": "$7.49"
  },
  {
    "name": "Go Tell the Bees That I Am Gone: A Novel (Outlander)",
    "price": "$23.71"
  },
  {
    "name": "Dune",
    "price": "$0.00 Free with Audible trial"
  },
  {
    "name": "All American Christmas",
    "price": "$18.92"
  },
  {
    "name": "Melissa & Doug Children's Book - Poke-a-Dot: Old MacDonald’s Farm (Board Book with Buttons…",
    "price": "$13.99"
  },
  {
    "name": "Atomic Habits: An Easy & Proven Way to Build Good Habits & Break Bad Ones",
    "price": "$11.98"
  },
  {
    "name": "Throne of Glass eBook Bundle: An 8 Book Bundle",
    "price": "$38.99"
  },
  {
    "name": "The 1619 Project: A New Origin Story",
    "price": "$23.17"
  },
  {
    "name": "It Ends With Us: A Novel",
    "price": "$9.47"
  },
  {
    "name": "Atlas of the Heart: Mapping Meaningful Connection and the Language of Human Experience",
    "price": "$19.48"
  },
  {
    "name": "Sold on a Monday: A Novel",
    "price": "$7.59"
  },
  {
    "name": "How to Draw 101 Animals (1)",
    "price": "$3.29"
  },
  {
    "name": "Laptop from Hell: Hunter Biden, Big Tech, and the Dirty Secrets the President Tried to Hide",
    "price": "$28.99"
  },
  {
    "name": "The Storyteller: Tales of Life and Music",
    "price": "$17.99"
  },
  {
    "name": "The Big Book of Silly Jokes for Kids",
    "price": "$5.99"
  },
  {
    "name": "If Animals Kissed Good Night",
    "price": "$4.44"
  },
  {
    "name": "The Christmas Pig",
    "price": "$12.49"
  },
  {
    "name": "The Eye of the World: Book One of The Wheel of Time",
    "price": "$0.00 Free with Audible trial"
  },
  {
    "name": "I Love You to the Moon and Back",
    "price": "$4.28"
  },
  {
    "name": "How to Catch a Mermaid",
    "price": "$4.96"
  },
  {
    "name": "A Not So Meet Cute",
    "price": "$4.99"
  },
  {
    "name": "Greenlights",
    "price": "$0.00 Free with Audible trial"
  },
  {
    "name": "At First Light (Dr. Evan Wilding Book 1)",
    "price": "$4.99"
  },
  {
    "name": "I Am Confident, Brave & Beautiful: A Coloring Book for Girls",
    "price": "$6.99"
  },
  {
    "name": "Cat Kid Comic Club: Perspectives: A Graphic Novel (Cat Kid Comic Club #2): From the Creator of…",
    "price": "$8.62"
  },
  {
    "name": "The Judge's List: A Novel",
    "price": "$0.00 Free with Audible trial"
  },
  {
    "name": "Guinness World Records 2022",
    "price": "$14.97"
  },
  {
    "name": "The Very Hungry Caterpillar",
    "price": "$5.06"
  },
  {
    "name": "The Four Winds: A Novel",
    "price": "$14.99"
  },
  {
    "name": "The Lincoln Highway: A Novel",
    "price": "$18.84"
  },
  {
    "name": "My First Learn to Write Workbook: Practice for Kids with Pen Control, Line Tracing, Letters, and More!",
    "price": "$4.53"
  },
  {
    "name": "From Crook to Cook: Platinum Recipes from Tha Boss Dogg's Kitchen (Snoop Dogg…",
    "price": "$12.74"
  },
  {
    "name": "Ignite: A Grumpy Single Dad Romance",
    "price": "$2.99"
  },
  {
    "name": "The Worst Best Friend: A Small Town Romance",
    "price": "$2.99"
  },
  {
    "name": "The Stranger in the Lifeboat: A Novel",
    "price": "$11.99"
  },
  {
    "name": "Difficult Riddles For Smart Kids: 300 Difficult Riddles And Brain Teasers Families Will Love…",
    "price": "$5.99"
  },
  {
    "name": "Will",
    "price": "$0.00 Free with Audible trial"
  },
  {
    "name": "The Real Anthony Fauci: Bill Gates, Big Pharma, and the Global War on Democracy and Public…",
    "price": "$20.88"
  },
  {
    "name": "Big Shot Diary of a Wimpy Kid Book 16",
    "price": "$7.49"
  },
  {
    "name": "Go Tell the Bees That I Am Gone: A Novel (Outlander)",
    "price": "$23.71"
  },
  {
    "name": "Dune",
    "price": "$0.00 Free with Audible trial"
  },
  {
    "name": "All American Christmas",
    "price": "$18.92"
  },
  {
    "name": "Melissa & Doug Children's Book - Poke-a-Dot: Old MacDonald’s Farm (Board Book with Buttons…",
    "price": "$13.99"
  },
  {
    "name": "Atomic Habits: An Easy & Proven Way to Build Good Habits & Break Bad Ones",
    "price": "$11.98"
  },
  {
    "name": "Throne of Glass eBook Bundle: An 8 Book Bundle",
    "price": "$38.99"
  },
  {
    "name": "The 1619 Project: A New Origin Story",
    "price": "$23.17"
  },
  {
    "name": "It Ends With Us: A Novel",
    "price": "$9.47"
  },
  {
    "name": "Atlas of the Heart: Mapping Meaningful Connection and the Language of Human Experience",
    "price": "$19.48"
  },
  {
    "name": "Sold on a Monday: A Novel",
    "price": "$7.59"
  },
  {
    "name": "How to Draw 101 Animals (1)",
    "price": "$3.29"
  },
  {
    "name": "Laptop from Hell: Hunter Biden, Big Tech, and the Dirty Secrets the President Tried to Hide",
    "price": "$28.99"
  },
  {
    "name": "The Storyteller: Tales of Life and Music",
    "price": "$17.99"
  },
  {
    "name": "The Big Book of Silly Jokes for Kids",
    "price": "$5.99"
  },
  {
    "name": "If Animals Kissed Good Night",
    "price": "$4.44"
  },
  {
    "name": "The Christmas Pig",
    "price": "$12.49"
  },
  {
    "name": "The Eye of the World: Book One of The Wheel of Time",
    "price": "$0.00 Free with Audible trial"
  },
  {
    "name": "I Love You to the Moon and Back",
    "price": "$4.28"
  },
  {
    "name": "How to Catch a Mermaid",
    "price": "$4.96"
  },
  {
    "name": "A Not So Meet Cute",
    "price": "$4.99"
  },
  {
    "name": "Greenlights",
    "price": "$0.00 Free with Audible trial"
  },
  {
    "name": "At First Light (Dr. Evan Wilding Book 1)",
    "price": "$4.99"
  },
  {
    "name": "I Am Confident, Brave & Beautiful: A Coloring Book for Girls",
    "price": "$6.99"
  },
  {
    "name": "Cat Kid Comic Club: Perspectives: A Graphic Novel (Cat Kid Comic Club #2): From the Creator of…",
    "price": "$8.62"
  },
  {
    "name": "The Judge's List: A Novel",
    "price": "$0.00 Free with Audible trial"
  },
  {
    "name": "Guinness World Records 2022",
    "price": "$14.97"
  },
  {
    "name": "The Very Hungry Caterpillar",
    "price": "$5.06"
  },
  {
    "name": "The Four Winds: A Novel",
    "price": "$14.99"
  },
  {
    "name": "Harry Potter Paperback Box Set (Books 1-7)",
    "price": "$39.99"
  },
  {
    "name": "The Lincoln Highway: A Novel",
    "price": "$18.84"
  },
  {
    "name": "My First Learn to Write Workbook: Practice for Kids with Pen Control, Line Tracing, Letters, and More!",
    "price": "$4.53"
  },
  {
    "name": "How to Catch a Unicorn",
    "price": "$5.49"
  },
  {
    "name": "From Crook to Cook: Platinum Recipes from Tha Boss Dogg's Kitchen (Snoop Dogg…",
    "price": "$12.74"
  },
  {
    "name": "Ignite: A Grumpy Single Dad Romance",
    "price": "$2.99"
  },
  {
    "name": "The Seven Husbands of Evelyn Hugo: A Novel",
    "price": "$9.42"
  },
  {
    "name": "The Worst Best Friend: A Small Town Romance",
    "price": "$2.99"
  },
  {
    "name": "Little Blue Truck's Christmas",
    "price": "$11.98"
  },
  {
    "name": "The Stranger in the Lifeboat: A Novel",
    "price": "$11.99"
  },
  {
    "name": "Difficult Riddles For Smart Kids: 300 Difficult Riddles And Brain Teasers Families Will Love…",
    "price": "$5.99"
  },
  {
    "name": "Will",
    "price": "$0.00 Free with Audible trial"
  },
  {
    "name": "The Real Anthony Fauci: Bill Gates, Big Pharma, and the Global War on Democracy and Public…",
    "price": "$20.88"
  },
  {
    "name": "Big Shot Diary of a Wimpy Kid Book 16",
    "price": "$7.49"
  },
  {
    "name": "Go Tell the Bees That I Am Gone: A Novel (Outlander)",
    "price": "$23.71"
  },
  {
    "name": "Dune",
    "price": "$0.00 Free with Audible trial"
  },
  {
    "name": "All American Christmas",
    "price": "$18.92"
  },
  {
    "name": "Melissa & Doug Children's Book - Poke-a-Dot: Old MacDonald’s Farm (Board Book with Buttons…",
    "price": "$13.99"
  },
  {
    "name": "Atomic Habits: An Easy & Proven Way to Build Good Habits & Break Bad Ones",
    "price": "$11.98"
  },
  {
    "name": "Throne of Glass eBook Bundle: An 8 Book Bundle",
    "price": "$38.99"
  },
  {
    "name": "The 1619 Project: A New Origin Story",
    "price": "$23.17"
  },
  {
    "name": "It Ends With Us: A Novel",
    "price": "$9.47"
  },
  {
    "name": "Atlas of the Heart: Mapping Meaningful Connection and the Language of Human Experience",
    "price": "$19.48"
  },
  {
    "name": "Sold on a Monday: A Novel",
    "price": "$7.59"
  },
  {
    "name": "Laptop from Hell: Hunter Biden, Big Tech, and the Dirty Secrets the President Tried to Hide",
    "price": "$25.20"
  },
  {
    "name": "The Storyteller: Tales of Life and Music",
    "price": "$17.99"
  },
  {
    "name": "The Big Book of Silly Jokes for Kids",
    "price": "$5.99"
  },
  {
    "name": "If Animals Kissed Good Night",
    "price": "$4.44"
  },
  {
    "name": "The Christmas Pig",
    "price": "$12.49"
  },
  {
    "name": "The Eye of the World: Book One of The Wheel of Time",
    "price": "$0.00 Free with Audible trial"
  },
  {
    "name": "A Not So Meet Cute",
    "price": "$4.99"
  },
  {
    "name": "Greenlights",
    "price": "$0.00 Free with Audible trial"
  },
  {
    "name": "At First Light (Dr. Evan Wilding Book 1)",
    "price": "$4.99"
  },
  {
    "name": "I Am Confident, Brave & Beautiful: A Coloring Book for Girls",
    "price": "$6.99"
  },
  {
    "name": "Cat Kid Comic Club: Perspectives: A Graphic Novel (Cat Kid Comic Club #2): From the Creator of…",
    "price": "$8.62"
  },
  {
    "name": "The Judge's List: A Novel",
    "price": "$0.00 Free with Audible trial"
  },
  {
    "name": "Guinness World Records 2022",
    "price": "$14.97"
  },
  {
    "name": "The Very Hungry Caterpillar",
    "price": "$5.06"
  },
  {
    "name": "The Four Winds: A Novel",
    "price": "$14.99"
  },
  {
    "name": "The Lincoln Highway: A Novel",
    "price": "$18.84"
  },
  {
    "name": "My First Learn to Write Workbook: Practice for Kids with Pen Control, Line Tracing, Letters, and More!",
    "price": "$4.53"
  },
  {
    "name": "From Crook to Cook: Platinum Recipes from Tha Boss Dogg's Kitchen (Snoop Dogg…",
    "price": "$12.74"
  },
  {
    "name": "Ignite: A Grumpy Single Dad Romance",
    "price": "$2.99"
  },
  {
    "name": "The Worst Best Friend: A Small Town Romance",
    "price": "$2.99"
  },
  {
    "name": "The Stranger in the Lifeboat: A Novel",
    "price": "$11.99"
  },
  {
    "name": "Difficult Riddles For Smart Kids: 300 Difficult Riddles And Brain Teasers Families Will Love…",
    "price": "$5.99"
  },
  {
    "name": "Will",
    "price": "$0.00 Free with Audible trial"
  },
  {
    "name": "The Real Anthony Fauci: Bill Gates, Big Pharma, and the Global War on Democracy and Public…",
    "price": "$20.88"
  },
  {
    "name": "Big Shot Diary of a Wimpy Kid Book 16",
    "price": "$7.49"
  },
  {
    "name": "Go Tell the Bees That I Am Gone: A Novel (Outlander)",
    "price": "$23.71"
  },
  {
    "name": "Dune",
    "price": "$0.00 Free with Audible trial"
  },
  {
    "name": "All American Christmas",
    "price": "$18.92"
  },
  {
    "name": "Melissa & Doug Children's Book - Poke-a-Dot: Old MacDonald’s Farm (Board Book with Buttons…",
    "price": "$13.99"
  },
  {
    "name": "Atomic Habits: An Easy & Proven Way to Build Good Habits & Break Bad Ones",
    "price": "$11.98"
  },
  {
    "name": "Throne of Glass eBook Bundle: An 8 Book Bundle",
    "price": "$38.99"
  },
  {
    "name": "The 1619 Project: A New Origin Story",
    "price": "$23.17"
  },
  {
    "name": "It Ends With Us: A Novel",
    "price": "$9.47"
  },
  {
    "name": "Atlas of the Heart: Mapping Meaningful Connection and the Language of Human Experience",
    "price": "$19.48"
  },
  {
    "name": "Sold on a Monday: A Novel",
    "price": "$7.59"
  },
  {
    "name": "How to Draw 101 Animals (1)",
    "price": "$3.29"
  },
  {
    "name": "Laptop from Hell: Hunter Biden, Big Tech, and the Dirty Secrets the President Tried to Hide",
    "price": "$28.99"
  },
  {
    "name": "The Storyteller: Tales of Life and Music",
    "price": "$17.99"
  },
  {
    "name": "The Big Book of Silly Jokes for Kids",
    "price": "$5.99"
  },
  {
    "name": "If Animals Kissed Good Night",
    "price": "$4.44"
  },
  {
    "name": "The Christmas Pig",
    "price": "$12.49"
  },
  {
    "name": "The Eye of the World: Book One of The Wheel of Time",
    "price": "$0.00 Free with Audible trial"
  },
  {
    "name": "I Love You to the Moon and Back",
    "price": "$4.28"
  },
  {
    "name": "How to Catch a Mermaid",
    "price": "$4.96"
  },
  {
    "name": "A Not So Meet Cute",
    "price": "$4.99"
  },
  {
    "name": "Greenlights",
    "price": "$0.00 Free with Audible trial"
  },
  {
    "name": "At First Light (Dr. Evan Wilding Book 1)",
    "price": "$4.99"
  },
  {
    "name": "I Am Confident, Brave & Beautiful: A Coloring Book for Girls",
    "price": "$6.99"
  },
  {
    "name": "Cat Kid Comic Club: Perspectives: A Graphic Novel (Cat Kid Comic Club #2): From the Creator of…",
    "price": "$8.62"
  },
  {
    "name": "The Judge's List: A Novel",
    "price": "$0.00 Free with Audible trial"
  },
  {
    "name": "Guinness World Records 2022",
    "price": "$14.97"
  },
  {
    "name": "The Very Hungry Caterpillar",
    "price": "$5.06"
  },
  {
    "name": "The Four Winds: A Novel",
    "price": "$14.99"
  },
  {
    "name": "Harry Potter Paperback Box Set (Books 1-7)",
    "price": "$39.99"
  },
  {
    "name": "The Lincoln Highway: A Novel",
    "price": "$18.84"
  },
  {
    "name": "My First Learn to Write Workbook: Practice for Kids with Pen Control, Line Tracing, Letters, and More!",
    "price": "$4.53"
  },
  {
    "name": "How to Catch a Unicorn",
    "price": "$5.49"
  },
  {
    "name": "From Crook to Cook: Platinum Recipes from Tha Boss Dogg's Kitchen (Snoop Dogg…",
    "price": "$12.74"
  },
  {
    "name": "Ignite: A Grumpy Single Dad Romance",
    "price": "$2.99"
  },
  {
    "name": "The Seven Husbands of Evelyn Hugo: A Novel",
    "price": "$9.42"
  },
  {
    "name": "The Worst Best Friend: A Small Town Romance",
    "price": "$2.99"
  },
  {
    "name": "Little Blue Truck's Christmas",
    "price": "$11.98"
  },
  {
    "name": "The Stranger in the Lifeboat: A Novel",
    "price": "$11.99"
  },
  {
    "name": "Difficult Riddles For Smart Kids: 300 Difficult Riddles And Brain Teasers Families Will Love…",
    "price": "$5.99"
  },
  {
    "name": "Will",
    "price": "$0.00 Free with Audible trial"
  },
  {
    "name": "The Real Anthony Fauci: Bill Gates, Big Pharma, and the Global War on Democracy and Public Health (Children’s Health Defense)",
    "price": "$20.88"
  },
  {
    "name": "Big Shot Diary of a Wimpy Kid Book 16",
    "price": "$7.49"
  },
  {
    "name": "Go Tell the Bees That I Am Gone: A Novel (Outlander)",
    "price": "$23.71"
  },
  {
    "name": "Dune",
    "price": "$0.00 Free with Audible trial"
  },
  {
    "name": "All American Christmas",
    "price": "$18.92"
  },
  {
    "name": "Melissa & Doug Children's Book - Poke-a-Dot: Old MacDonald’s Farm (Board Book with Buttons…",
    "price": "$13.99"
  },
  {
    "name": "Atomic Habits: An Easy & Proven Way to Build Good Habits & Break Bad Ones",
    "price": "$11.98"
  },
  {
    "name": "Throne of Glass eBook Bundle: An 8 Book Bundle",
    "price": "$38.99"
  },
  {
    "name": "The 1619 Project: A New Origin Story",
    "price": "$23.17"
  },
  {
    "name": "It Ends With Us: A Novel",
    "price": "$9.47"
  },
  {
    "name": "Atlas of the Heart: Mapping Meaningful Connection and the Language of Human Experience",
    "price": "$19.48"
  },
  {
    "name": "Sold on a Monday: A Novel",
    "price": "$7.59"
  },
  {
    "name": "Laptop from Hell: Hunter Biden, Big Tech, and the Dirty Secrets the President Tried to Hide",
    "price": "$25.20"
  },
  {
    "name": "The Storyteller: Tales of Life and Music",
    "price": "$17.99"
  },
  {
    "name": "The Big Book of Silly Jokes for Kids",
    "price": "$5.99"
  },
  {
    "name": "If Animals Kissed Good Night",
    "price": "$4.44"
  },
  {
    "name": "The Christmas Pig",
    "price": "$12.49"
  },
  {
    "name": "The Eye of the World: Book One of The Wheel of Time",
    "price": "$0.00 Free with Audible trial"
  },
  {
    "name": "A Not So Meet Cute",
    "price": "$4.99"
  },
  {
    "name": "Greenlights",
    "price": "$0.00 Free with Audible trial"
  },
  {
    "name": "At First Light (Dr. Evan Wilding Book 1)",
    "price": "$4.99"
  },
  {
    "name": "I Am Confident, Brave & Beautiful: A Coloring Book for Girls",
    "price": "$6.99"
  },
  {
    "name": "Cat Kid Comic Club: Perspectives: A Graphic Novel (Cat Kid Comic Club #2): From the Creator of…",
    "price": "$8.62"
  },
  {
    "name": "The Judge's List: A Novel",
    "price": "$0.00 Free with Audible trial"
  },
  {
    "name": "Guinness World Records 2022",
    "price": "$14.97"
  },
  {
    "name": "The Very Hungry Caterpillar",
    "price": "$5.06"
  },
  {
    "name": "The Four Winds: A Novel",
    "price": "$14.99"
  },
  {
    "name": "The Lincoln Highway: A Novel",
    "price": "$18.84"
  },
  {
    "name": "My First Learn to Write Workbook: Practice for Kids with Pen Control, Line Tracing, Letters, and More!",
    "price": "$4.53"
  },
  {
    "name": "From Crook to Cook: Platinum Recipes from Tha Boss Dogg's Kitchen (Snoop Dogg…",
    "price": "$12.74"
  },
  {
    "name": "Ignite: A Grumpy Single Dad Romance",
    "price": "$2.99"
  },
  {
    "name": "The Worst Best Friend: A Small Town Romance",
    "price": "$2.99"
  },
  {
    "name": "The Stranger in the Lifeboat: A Novel",
    "price": "$11.99"
  },
  {
    "name": "Difficult Riddles For Smart Kids: 300 Difficult Riddles And Brain Teasers Families Will Love…",
    "price": "$5.99"
  },
  {
    "name": "Will",
    "price": "$0.00 Free with Audible trial"
  },
  {
    "name": "The Real Anthony Fauci: Bill Gates, Big Pharma, and the Global War on Democracy and Public…",
    "price": "$20.88"
  },
  {
    "name": "Big Shot Diary of a Wimpy Kid Book 16",
    "price": "$7.49"
  },
  {
    "name": "Go Tell the Bees That I Am Gone: A Novel (Outlander)",
    "price": "$23.71"
  },
  {
    "name": "Dune",
    "price": "$0.00 Free with Audible trial"
  },
  {
    "name": "All American Christmas",
    "price": "$18.92"
  },
  {
    "name": "Melissa & Doug Children's Book - Poke-a-Dot: Old MacDonald’s Farm (Board Book with Buttons…",
    "price": "$13.99"
  },
  {
    "name": "Atomic Habits: An Easy & Proven Way to Build Good Habits & Break Bad Ones",
    "price": "$11.98"
  },
  {
    "name": "Throne of Glass eBook Bundle: An 8 Book Bundle",
    "price": "$38.99"
  },
  {
    "name": "The 1619 Project: A New Origin Story",
    "price": "$23.17"
  },
  {
    "name": "It Ends With Us: A Novel",
    "price": "$9.47"
  },
  {
    "name": "Atlas of the Heart: Mapping Meaningful Connection and the Language of Human Experience",
    "price": "$19.48"
  },
  {
    "name": "Sold on a Monday: A Novel",
    "price": "$7.59"
  },
  {
    "name": "How to Draw 101 Animals (1)",
    "price": "$3.29"
  },
  {
    "name": "Laptop from Hell: Hunter Biden, Big Tech, and the Dirty Secrets the President Tried to Hide",
    "price": "$28.99"
  },
  {
    "name": "The Storyteller: Tales of Life and Music",
    "price": "$17.99"
  },
  {
    "name": "The Big Book of Silly Jokes for Kids",
    "price": "$5.99"
  },
  {
    "name": "If Animals Kissed Good Night",
    "price": "$4.44"
  },
  {
    "name": "The Christmas Pig",
    "price": "$12.49"
  },
  {
    "name": "The Eye of the World: Book One of The Wheel of Time",
    "price": "$0.00 Free with Audible trial"
  },
  {
    "name": "I Love You to the Moon and Back",
    "price": "$4.28"
  },
  {
    "name": "How to Catch a Mermaid",
    "price": "$4.96"
  },
  {
    "name": "A Not So Meet Cute",
    "price": "$4.99"
  },
  {
    "name": "Greenlights",
    "price": "$0.00 Free with Audible trial"
  },
  {
    "name": "At First Light (Dr. Evan Wilding Book 1)",
    "price": "$4.99"
  },
  {
    "name": "I Am Confident, Brave & Beautiful: A Coloring Book for Girls",
    "price": "$6.99"
  },
  {
    "name": "Cat Kid Comic Club: Perspectives: A Graphic Novel (Cat Kid Comic Club #2): From the Creator of…",
    "price": "$8.62"
  },
  {
    "name": "The Judge's List: A Novel",
    "price": "$0.00 Free with Audible trial"
  },
  {
    "name": "Guinness World Records 2022",
    "price": "$14.97"
  },
  {
    "name": "The Very Hungry Caterpillar",
    "price": "$5.06"
  },
  {
    "name": "The Four Winds: A Novel",
    "price": "$14.99"
  },
  {
    "name": "Harry Potter Paperback Box Set (Books 1-7)",
    "price": "$39.99"
  },
  {
    "name": "The Lincoln Highway: A Novel",
    "price": "$18.84"
  },
  {
    "name": "My First Learn to Write Workbook: Practice for Kids with Pen Control, Line Tracing, Letters, and More!",
    "price": "$4.53"
  },
  {
    "name": "How to Catch a Unicorn",
    "price": "$5.49"
  },
  {
    "name": "From Crook to Cook: Platinum Recipes from Tha Boss Dogg's Kitchen (Snoop Dogg…",
    "price": "$12.74"
  },
  {
    "name": "Ignite: A Grumpy Single Dad Romance",
    "price": "$2.99"
  },
  {
    "name": "The Seven Husbands of Evelyn Hugo: A Novel",
    "price": "$9.42"
  },
  {
    "name": "The Worst Best Friend: A Small Town Romance",
    "price": "$2.99"
  },
  {
    "name": "Little Blue Truck's Christmas",
    "price": "$11.98"
  },
  {
    "name": "The Stranger in the Lifeboat: A Novel",
    "price": "$11.99"
  },
  {
    "name": "Difficult Riddles For Smart Kids: 300 Difficult Riddles And Brain Teasers Families Will Love…",
    "price": "$5.99"
  },
  {
    "name": "Will",
    "price": "$0.00 Free with Audible trial"
  },
  {
    "name": "Atlas of the Heart: Mapping Meaningful Connection and the Language of Human Experience",
    "price": "$19.48"
  },
  {
    "name": "The Real Anthony Fauci: Bill Gates, Big Pharma, and the Global War on Democracy and Public…",
    "price": "$21.36"
  },
  {
    "name": "Big Shot Diary of a Wimpy Kid Book 16",
    "price": "$7.49"
  },
  {
    "name": "All American Christmas",
    "price": "$18.92"
  },
  {
    "name": "Go Tell the Bees That I Am Gone: A Novel (Outlander Book 9)",
    "price": "$15.99"
  },
  {
    "name": "If You Tell: A True Story of Murder, Family Secrets, and the Unbreakable Bond of Sisterhood",
    "price": "$4.99"
  },
  {
    "name": "The Last One Home",
    "price": "$3.99"
  },
  {
    "name": "Dune",
    "price": "$0.00 Free with Audible trial"
  },
  {
    "name": "Atomic Habits: An Easy & Proven Way to Build Good Habits & Break Bad Ones",
    "price": "$11.98"
  },
  {
    "name": "Laptop from Hell: Hunter Biden, Big Tech, and the Dirty Secrets the President Tried to Hide",
    "price": "$19.24"
  },
  {
    "name": "Sold on a Monday: A Novel",
    "price": "$7.59"
  },
  {
    "name": "It Ends with Us: A Novel",
    "price": "$9.47"
  },
  {
    "name": "The Storyteller: Tales of Life and Music",
    "price": "$17.99"
  },
  {
    "name": "The 1619 Project: A New Origin Story",
    "price": "$23.17"
  },
  {
    "name": "The Last Green Valley: A Novel",
    "price": "$5.99"
  },
  {
    "name": "The Cipher (Nina Guerrera Book 1)",
    "price": "$4.99"
  },
  {
    "name": "Cat Kid Comic Club: Perspectives: A Graphic Novel (Cat Kid Comic Club #2): From the Creator of…",
    "price": "$8.62"
  },
  {
    "name": "If Animals Kissed Good Night",
    "price": "$4.44"
  },
  {
    "name": "The Christmas Pig",
    "price": "$12.49"
  },
  {
    "name": "The Big Book of Silly Jokes for Kids",
    "price": "$5.99"
  },
  {
    "name": "Greenlights",
    "price": "$0.00 Free with Audible trial"
  },
  {
    "name": "From Crook to Cook: Platinum Recipes from Tha Boss Dogg's Kitchen (Snoop Dogg…",
    "price": "$12.74"
  },
  {
    "name": "A Not So Meet Cute",
    "price": "$4.99"
  },
  {
    "name": "Knight's Ransom (The First Argentines Book 1)",
    "price": "$5.99"
  },
  {
    "name": "The Eye of the World: Book One of The Wheel of Time",
    "price": "$0.00 Free with Audible trial"
  },
  {
    "name": "Ignite: A Grumpy Single Dad Romance",
    "price": "$2.99"
  },
  {
    "name": "I Am Confident, Brave & Beautiful: A Coloring Book for Girls",
    "price": "$6.99"
  },
  {
    "name": "Melissa & Doug Children's Book - Poke-a-Dot: Old MacDonald’s Farm (Board Book with Buttons…",
    "price": "$13.99"
  },
  {
    "name": "The Devil Wears Black",
    "price": "$4.99"
  },
  {
    "name": "The Lincoln Highway: A Novel",
    "price": "$18.28"
  },
  {
    "name": "The Venice Sketchbook: A Novel",
    "price": "$5.99"
  },
  {
    "name": "The Very Hungry Caterpillar",
    "price": "$5.06"
  },
  {
    "name": "At First Light (Dr. Evan Wilding Book 1)",
    "price": "$4.99"
  },
  {
    "name": "The Judge's List: A Novel",
    "price": "$0.00 Free with Audible trial"
  },
  {
    "name": "Guinness World Records 2022",
    "price": "$14.97"
  },
  {
    "name": "Will",
    "price": "$0.00 Free with Audible trial"
  },
  {
    "name": "The Last One Home",
    "price": "$3.99"
  },
  {
    "name": "If You Tell: A True Story of Murder, Family Secrets, and the Unbreakable Bond of Sisterhood",
    "price": "$4.99"
  },
  {
    "name": "Go Tell the Bees That I Am Gone: A Novel (Outlander Book 9)",
    "price": "$15.99"
  },
  {
    "name": "Dune",
    "price": "$0.00 Free with Audible trial"
  },
  {
    "name": "The Storyteller: Tales of Life and Music",
    "price": "$17.98"
  },
  {
    "name": "Sold on a Monday: A Novel",
    "price": "$7.59"
  },
  {
    "name": "The Last Green Valley: A Novel",
    "price": "$5.99"
  },
  {
    "name": "The Cipher (Nina Guerrera Book 1)",
    "price": "$4.99"
  },
  {
    "name": "Greenlights",
    "price": "$0.00 Free with Audible trial"
  },
  {
    "name": "Ignite: A Grumpy Single Dad Romance",
    "price": "$4.99"
  },
  {
    "name": "The Venice Sketchbook: A Novel",
    "price": "$5.99"
  },
  {
    "name": "The Eye of the World: Book One of The Wheel of Time",
    "price": "$0.00 Free with Audible trial"
  },
  {
    "name": "A Not So Meet Cute",
    "price": "$4.99"
  },
  {
    "name": "The Devil Wears Black",
    "price": "$4.99"
  },
  {
    "name": "The Lincoln Highway: A Novel",
    "price": "$18.28"
  },
  {
    "name": "Knight's Ransom (The First Argentines Book 1)",
    "price": "$5.99"
  },
  {
    "name": "Write My Name Across the Sky: A Novel",
    "price": "$5.99"
  },
  {
    "name": "Difficult Riddles For Smart Kids: 300 Difficult Riddles And Brain Teasers Families Will Love…",
    "price": "$6.74"
  },
  {
    "name": "At First Light (Dr. Evan Wilding Book 1)",
    "price": "$4.99"
  },
  {
    "name": "Will",
    "price": "$0.00 Free with Audible trial"
  },
  {
    "name": "The Last One Home",
    "price": "$3.99"
  },
  {
    "name": "If You Tell: A True Story of Murder, Family Secrets, and the Unbreakable Bond of Sisterhood",
    "price": "$4.99"
  },
  {
    "name": "Go Tell the Bees That I Am Gone: A Novel (Outlander Book 9)",
    "price": "$15.99"
  },
  {
    "name": "Dune",
    "price": "$0.00 Free with Audible trial"
  },
  {
    "name": "The Storyteller: Tales of Life and Music",
    "price": "$17.98"
  },
  {
    "name": "Sold on a Monday: A Novel",
    "price": "$7.59"
  },
  {
    "name": "The Last Green Valley: A Novel",
    "price": "$5.99"
  },
  {
    "name": "The Cipher (Nina Guerrera Book 1)",
    "price": "$4.99"
  },
  {
    "name": "Greenlights",
    "price": "$0.00 Free with Audible trial"
  },
  {
    "name": "Ignite: A Grumpy Single Dad Romance",
    "price": "$4.99"
  },
  {
    "name": "The Venice Sketchbook: A Novel",
    "price": "$5.99"
  },
  {
    "name": "The Eye of the World: Book One of The Wheel of Time",
    "price": "$0.00 Free with Audible trial"
  },
  {
    "name": "A Not So Meet Cute",
    "price": "$4.99"
  },
  {
    "name": "The Devil Wears Black",
    "price": "$4.99"
  },
  {
    "name": "The Lincoln Highway: A Novel",
    "price": "$18.28"
  },
  {
    "name": "Knight's Ransom (The First Argentines Book 1)",
    "price": "$5.99"
  },
  {
    "name": "Write My Name Across the Sky: A Novel",
    "price": "$5.99"
  },
  {
    "name": "Difficult Riddles For Smart Kids: 300 Difficult Riddles And Brain Teasers Families Will Love…",
    "price": "$6.74"
  },
  {
    "name": "At First Light (Dr. Evan Wilding Book 1)",
    "price": "$4.99"
  }
]